zamzar/__init__.py
zamzar/api_client.py
zamzar/api_response.py
zamzar/configuration.py
zamzar/exceptions.py
zamzar/py.typed
zamzar/rest.py
zamzar/api/__init__.py
zamzar/api/account_api.py
zamzar/api/files_api.py
zamzar/api/formats_api.py
zamzar/api/imports_api.py
zamzar/api/jobs_api.py
zamzar/api/welcome_api.py
zamzar/facade/__init__.py
zamzar/facade/account_service.py
zamzar/facade/file_manager.py
zamzar/facade/files_service.py
zamzar/facade/formats_service.py
zamzar/facade/import_manager.py
zamzar/facade/imports_service.py
zamzar/facade/job_manager.py
zamzar/facade/job_status.py
zamzar/facade/jobs_service.py
zamzar/facade/successful_jobs_service.py
zamzar/facade/welcome_service.py
zamzar/facade/zamzar_client.py
zamzar/facade/_internal/__init__.py
zamzar/facade/_internal/awaitable.py
zamzar/facade/_internal/zamzar_pool_manager.py
zamzar/models/__init__.py
zamzar/models/account.py
zamzar/models/account_plan.py
zamzar/models/error.py
zamzar/models/error_context.py
zamzar/models/errors.py
zamzar/models/export.py
zamzar/models/failure.py
zamzar/models/file.py
zamzar/models/files.py
zamzar/models/format.py
zamzar/models/format_targets_inner.py
zamzar/models/formats.py
zamzar/models/imports.py
zamzar/models/job.py
zamzar/models/jobs.py
zamzar/models/model_import.py
zamzar/models/paging_numeric.py
zamzar/models/paging_string.py
zamzar/models/welcome200_response.py
zamzar/pagination/__init__.py
zamzar/pagination/anchor.py
zamzar/pagination/paged.py
zamzar-1.1.0.dist-info/LICENSE
zamzar-1.1.0.dist-info/METADATA
zamzar-1.1.0.dist-info/WHEEL
zamzar-1.1.0.dist-info/top_level.txt
zamzar-1.1.0.dist-info/RECORD
