Metadata-Version: 2.1
Name: zamzar
Version: 1.1.0
Summary: Official Python client for the Zamzar API
Home-page: https://github.com/zamzar/zamzar-python
Author: Zamzar
Author-email: api-sdks@zamzar.com
License: MIT
Keywords: Zamzar,Zamzar API,File Conversion,File Utilities,Convert
License-File: LICENSE
Requires-Dist: urllib3 <2.1.0,>=1.25.3
Requires-Dist: python-dateutil
Requires-Dist: pydantic >=2
Requires-Dist: typing-extensions >=4.7.1
